pywe_component_ticket/__init__.py
pywe_component_ticket/baseticket.py
pywe_component_ticket/pyweticket.py
pywe_component_ticket-1.0.0.dist-info/DESCRIPTION.rst
pywe_component_ticket-1.0.0.dist-info/METADATA
pywe_component_ticket-1.0.0.dist-info/RECORD
pywe_component_ticket-1.0.0.dist-info/WHEEL
pywe_component_ticket-1.0.0.dist-info/metadata.json
pywe_component_ticket-1.0.0.dist-info/top_level.txt
