Metadata-Version: 2.0
Name: pywe-component-ticket
Version: 1.0.0
Summary: Wechat Component Ticket Module for Python.
Home-page: https://github.com/sdkwe/pywe-component-ticket
Author: Hackathon
Author-email: kimi.huang@brightcells.com
License: UNKNOWN
Keywords: Wechat Weixin Component Ticket
Platform: UNKNOWN
Classifier: License :: OSI Approved :: BSD License
Classifier: Programming Language :: Python
Classifier: Programming Language :: Python :: 2
Classifier: Programming Language :: Python :: 2.6
Classifier: Programming Language :: Python :: 2.7
Classifier: Programming Language :: Python :: 3
Classifier: Programming Language :: Python :: 3.2
Classifier: Programming Language :: Python :: 3.3
Classifier: Programming Language :: Python :: 3.4
Classifier: Programming Language :: Python :: 3.5
Classifier: Programming Language :: Python :: 3.6
Classifier: Topic :: Software Development :: Libraries :: Python Modules
Requires-Dist: pywe-base
Requires-Dist: pywe-decrypt (>=1.1.0)
Requires-Dist: pywe-storage
Requires-Dist: pywe-token (>=1.0.7)
Requires-Dist: pywe-xml (>=1.0.3)
